today_in_nature/__init__.py
today_in_nature/data_loader.py
today_in_nature/main.py
today_in_nature/utils.py
today_in_nature-1.0.1.dist-info/LICENSE
today_in_nature-1.0.1.dist-info/METADATA
today_in_nature-1.0.1.dist-info/WHEEL
today_in_nature-1.0.1.dist-info/entry_points.txt
today_in_nature-1.0.1.dist-info/RECORD
